modbus_scale_server/__init__.py
modbus_scale_server/modbus_scale_server.py
modbus_scale_server-1.0.10.dist-info/licenses/LICENSE.md
modbus_scale_server-1.0.10.dist-info/METADATA
modbus_scale_server-1.0.10.dist-info/WHEEL
modbus_scale_server-1.0.10.dist-info/top_level.txt
modbus_scale_server-1.0.10.dist-info/RECORD
