Metadata-Version: 2.4
Name: modbus-scale-server
Version: 1.0.10
Summary: Weigh scale Modbus Ethernet server daemon
Author-email: Rodney Elliott <rodney.elliott@canterbury.ac.nz>
License-Expression: GPL-3.0-or-later
Project-URL: Homepage, https://gitlab.com/uc_mech_wing/robotics_control_lab/uc-02-2024/modbus_scale_server
Project-URL: Issues, https://gitlab.com/uc_mech_wing/robotics_control_lab/uc-02-2024/modbus_scale_server/-/issues
Keywords: Modbus,Raspberry Pi,Scale
Classifier: Environment :: Console
Classifier: Intended Audience :: Developers
Classifier: Intended Audience :: Education
Classifier: Operating System :: POSIX :: Linux
Classifier: Programming Language :: Python :: 3
Requires-Python: >=3.9
License-File: LICENSE.md
Requires-Dist: pyModbusTCP==0.2.1
Requires-Dist: smbus==1.1.post2
Dynamic: license-file
